botworks/__init__.py
botworks/botworks.py
botworks/config_constants.py
botworks/channel/Channel.py
botworks/channel/__init__.py
botworks/chat/EventTypes.py
botworks/chat/InteractionDefinition.py
botworks/chat/Response.py
botworks/chat/Trigger.py
botworks/chat/__init__.py
botworks/slack/Clack.py
botworks/slack/MessageHandler.py
botworks/slack/Payload.py
botworks/slack/__init__.py
botworks-0.1.8.dist-info/METADATA
botworks-0.1.8.dist-info/RECORD
botworks-0.1.8.dist-info/WHEEL
botworks-0.1.8.dist-info/top_level.txt
sampleconfig/__init__.py
sampleconfig/gameofthrones.py
sampleconfig/samplebot.py
test/__init__.py
test/botworks/__init__.py
test/botworks/chat/InteractionDefinitionTest.py
test/botworks/chat/ResponseTest.py
test/botworks/chat/TriggerTest.py
test/botworks/chat/__init__.py
