Metadata-Version: 2.1
Name: botworks
Version: 0.1.8
Summary: Slack bot framework
Home-page: https://github.com/doubleyuhtee/botworks
Author: William Hanson
Author-email: 42045551+doubleyuhtee@users.noreply.github.com
License: UNKNOWN
Platform: UNKNOWN
Classifier: Programming Language :: Python :: 3
Classifier: License :: OSI Approved :: MIT License
Classifier: Operating System :: OS Independent
Classifier: Development Status :: 4 - Beta
